cpyMSpec/__init__.py
cpyMSpec/ims.h
cpyMSpec/legacy_interface.py
cpyMSpec/libms_cffi.dylib
cpyMSpec/spectrum.py
cpyMSpec/utils.py
cpyMSpec/.dylibs/libgcc_s.1.dylib
cpyMSpec/.dylibs/libstdc++.6.dylib
cpyMSpec-0.4.2.dist-info/DESCRIPTION.rst
cpyMSpec-0.4.2.dist-info/METADATA
cpyMSpec-0.4.2.dist-info/metadata.json
cpyMSpec-0.4.2.dist-info/RECORD
cpyMSpec-0.4.2.dist-info/top_level.txt
cpyMSpec-0.4.2.dist-info/WHEEL
